importdoc/__init__.py
importdoc/banner.py
importdoc/cli.py
importdoc/modules/__init__.py
importdoc/modules/analysis.py
importdoc/modules/autofix.py
importdoc/modules/cache.py
importdoc/modules/confidence.py
importdoc/modules/config.py
importdoc/modules/diagnostics.py
importdoc/modules/discovery.py
importdoc/modules/plugin.py
importdoc/modules/processor.py
importdoc/modules/reporting.py
importdoc/modules/runner.py
importdoc/modules/schemas.py
importdoc/modules/telemetry.py
importdoc/modules/utils.py
importdoc/modules/worker.py
importdoc-4.0.1.dist-info/METADATA
importdoc-4.0.1.dist-info/WHEEL
importdoc-4.0.1.dist-info/entry_points.txt
importdoc-4.0.1.dist-info/RECORD
