Metadata-Version: 2.4
Name: importdoc
Version: 4.0.1
Summary: Advanced Python import diagnostic tool with deep analysis, subprocess isolation, auto-fixing suggestions, and CI-ready enforcement.
Project-URL: Homepage, https://github.com/dhruv13x/importdoc
Project-URL: Repository, https://github.com/dhruv13x/importdoc
Project-URL: Issues, https://github.com/dhruv13x/importdoc/issues
Project-URL: Documentation, https://pypi.org/project/importdoc
Author-email: dhruv13x <dhruv13x@gmail.com>
License: MIT
Classifier: Programming Language :: Python :: 3
Classifier: Programming Language :: Python :: 3.10
Classifier: Programming Language :: Python :: 3.11
Classifier: Programming Language :: Python :: 3.12
Requires-Python: >=3.10
Requires-Dist: jsonschema>=4.0.0
Requires-Dist: rich>=10.0.0
Requires-Dist: tomli>=2.0.0; python_version < '3.11'
Requires-Dist: tqdm>=4.0.0
Provides-Extra: dev
Requires-Dist: black>=24.3.0; extra == 'dev'
Requires-Dist: mypy>=1.11.0; extra == 'dev'
Requires-Dist: pyfakefs>=5.0.0; extra == 'dev'
Requires-Dist: pytest-asyncio>=0.23.0; extra == 'dev'
Requires-Dist: pytest-cov>=5.0.0; extra == 'dev'
Requires-Dist: pytest-json-report>=1.5.0; extra == 'dev'
Requires-Dist: pytest-mock>=3.10.0; extra == 'dev'
Requires-Dist: pytest-timeout>=2.2.0; extra == 'dev'
Requires-Dist: pytest>=8.0.0; extra == 'dev'
Requires-Dist: pyyaml>=6.0; extra == 'dev'
Requires-Dist: ruff>=0.6.0; extra == 'dev'
Requires-Dist: types-pyyaml>=6.0; extra == 'dev'
